vizing/__init__.py
vizing-0.2.1.dist-info/METADATA
vizing-0.2.1.dist-info/WHEEL
vizing-0.2.1.dist-info/RECORD
