Metadata-Version: 2.1
Name: vizing
Version: 0.2.1
Summary: Constraint-based list-colouring in Python.
Author: Matthew Henderson
Author-email: matthew.james.henderson@gmail.com
Requires-Python: >=3.10,<4.0
Classifier: Programming Language :: Python :: 3
Classifier: Programming Language :: Python :: 3.10
Classifier: Programming Language :: Python :: 3.11
Classifier: Programming Language :: Python :: 3.12
Classifier: Programming Language :: Python :: 3.13
Requires-Dist: listcolouring (>=0.2.0,<0.3.0)
Requires-Dist: networkx (>=3.2.1,<4.0.0)
Requires-Dist: python-constraint (>=1.4.0,<2.0.0)
